{"ch": "market.ETC_CW.kline.1min", "data": [{"amount": 82.58641216821678, "close": 8.477, "count": 4, "high": 8.477, "id": 1579994280, "low": 8.465, "open": 8.465, "vol": 70}, {"amount": 4.716981132075472, "close": 8.48, "count": 1, "high": 8.48, "id": 1579994340, "low": 8.48, "open": 8.48, "vol": 4}, {"amount": 11.802195208308746, "close": 8.473, "count": 1, "high": 8.473, "id": 1579994400, "low": 8.473, "open": 8.473, "vol": 10}, {"amount": 396.70341613026727, "close": 8.473, "count": 5, "high": 8.473, "id": 1579994460, "low": 8.469, "open": 8.47, "vol": 336}, {"amount": 581.6135448208017, "close": 8.503, "count": 14, "high": 8.503, "id": 1579994520, "low": 8.476, "open": 8.478, "vol": 494}, {"amount": 21.15711294455256, "close": 8.505, "count": 2, "high": 8.51, "id": 1579994580, "low": 8.505, "open": 8.51, "vol": 18}, {"amount": 5001.5008894904995, "close": 8.506, "count": 31, "high": 8.512, "id": 1579994640, "low": 8.505, "open": 8.505, "vol": 4254}, {"amount": 14.109070983956686, "close": 8.505, "count": 2, "high": 8.506, "id": 1579994700, "low": 8.505, "open": 8.506, "vol": 12}, {"amount": 166.99546061365777, "close": 8.503, "count": 2, "high": 8.511, "id": 1579994760, "low": 8.503, "open": 8.511, "vol": 142}, {"amount": 4995.208329631467, "close": 8.501, "count": 6, "high": 8.505, "id": 1579994820, "low": 8.5, "open": 8.505, "vol": 4246}, {"amount": 65.88927417066368, "close": 8.499, "count": 2, "high": 8.5, "id": 1579994880, "low": 8.499, "open": 8.5, "vol": 56}, {"amount": 1127.6158560263814, "close": 8.476, "count": 8, "high": 8.492, "id": 1579994940, "low": 8.472, "open": 8.492, "vol": 956}, {"amount": 560.8820740173355, "close": 8.491, "count": 13, "high": 8.491, "id": 1579995000, "low": 8.478, "open": 8.478, "vol": 476}, {"amount": 16.494985019461133, "close": 8.49, "count": 3, "high": 8.49, "id": 1579995060, "low": 8.484, "open": 8.487, "vol": 14}, {"amount": 155.4800872668746, "close": 8.48, "count": 4, "high": 8.49, "id": 1579995120, "low": 8.48, "open": 8.49, "vol": 132}, {"amount": 9.433962264150944, "close": 8.48, "count": 1, "high": 8.48, "id": 1579995180, "low": 8.48, "open": 8.48, "vol": 8}, {"amount": 129.58112156178768, "close": 8.489, "count": 2, "high": 8.489, "id": 1579995240, "low": 8.486, "open": 8.486, "vol": 110}, {"amount": 63.612289011613655, "close": 8.492, "count": 4, "high": 8.492, "id": 1579995300, "low": 8.484, "open": 8.484, "vol": 54}, {"amount": 42.4167107727852, "close": 8.484, "count": 4, "high": 8.493, "id": 1579995360, "low": 8.484, "open": 8.493, "vol": 36}, {"amount": 9.428403064230995, "close": 8.485, "count": 1, "high": 8.485, "id": 1579995420, "low": 8.485, "open": 8.485, "vol": 8}, {"amount": 1179.1535850489538, "close": 8.476, "count": 8, "high": 8.487, "id": 1579995480, "low": 8.476, "open": 8.487, "vol": 1000}, {"amount": 14.159849005425585, "close": 8.474, "count": 2, "high": 8.475, "id": 1579995540, "low": 8.474, "open": 8.475, "vol": 12}, {"amount": 330.6164657797298, "close": 8.466, "count": 6, "high": 8.474, "id": 1579995600, "low": 8.466, "open": 8.474, "vol": 280}, {"amount": 11.810558639423645, "close": 8.467, "count": 1, "high": 8.467, "id": 1579995660, "low": 8.467, "open": 8.467, "vol": 10}, {"amount": 945.3727073534982, "close": 8.46, "count": 6, "high": 8.469, "id": 1579995720, "low": 8.46, "open": 8.469, "vol": 800}, {"amount": 7.088009450679268, "close": 8.465, "count": 1, "high": 8.465, "id": 1579995780, "low": 8.465, "open": 8.465, "vol": 6}, {"amount": 385.3372040902674, "close": 8.46, "count": 3, "high": 8.465, "id": 1579995840, "low": 8.46, "open": 8.465, "vol": 326}, {"amount": 168.0428994379919, "close": 8.447, "count": 4, "high": 8.458, "id": 1579995900, "low": 8.447, "open": 8.458, "vol": 142}, {"amount": 122.98008911391317, "close": 8.457, "count": 2, "high": 8.457, "id": 1579995960, "low": 8.448, "open": 8.448, "vol": 104}, {"amount": 1190.5297458739258, "close": 8.448, "count": 4, "high": 8.456, "id": 1579996020, "low": 8.448, "open": 8.456, "vol": 1006}, {"amount": 2.3671440407148774, "close": 8.449, "count": 1, "high": 8.449, "id": 1579996080, "low": 8.449, "open": 8.449, "vol": 2}, {"amount": 1096.944964843119, "close": 8.462, "count": 10, "high": 8.466, "id": 1579996140, "low": 8.458, "open": 8.458, "vol": 928}, {"amount": 1406.7769716074502, "close": 8.472, "count": 13, "high": 8.478, "id": 1579996200, "low": 8.455, "open": 8.455, "vol": 1192}, {"amount": 254.78766017208474, "close": 8.473, "count": 9, "high": 8.48, "id": 1579996260, "low": 8.472, "open": 8.477, "vol": 216}, {"amount": 122.78630460448642, "close": 8.47, "count": 3, "high": 8.47, "id": 1579996320, "low": 8.47, "open": 8.47, "vol": 104}, {"amount": 94.56265072632293, "close": 8.465, "count": 4, "high": 8.465, "id": 1579996380, "low": 8.457, "open": 8.46, "vol": 80}, {"amount": 250.74230194942243, "close": 8.453, "count": 5, "high": 8.464, "id": 1579996440, "low": 8.453, "open": 8.464, "vol": 212}, {"amount": 5407.123591646645, "close": 8.431, "count": 31, "high": 8.451, "id": 1579996500, "low": 8.419, "open": 8.451, "vol": 4556}, {"amount": 255.97086473015116, "close": 8.432, "count": 7, "high": 8.442, "id": 1579996560, "low": 8.432, "open": 8.432, "vol": 216}, {"amount": 289.2220095852391, "close": 8.434, "count": 5, "high": 8.438, "id": 1579996620, "low": 8.432, "open": 8.432, "vol": 244}, {"amount": 113.83596832142685, "close": 8.433, "count": 5, "high": 8.434, "id": 1579996680, "low": 8.426, "open": 8.434, "vol": 96}, {"amount": 5271.8561095234145, "close": 8.413, "count": 16, "high": 8.429, "id": 1579996740, "low": 8.41, "open": 8.429, "vol": 4434}, {"amount": 1985.9400557183747, "close": 8.37, "count": 21, "high": 8.409, "id": 1579996800, "low": 8.37, "open": 8.409, "vol": 1666}, {"amount": 2752.072809790003, "close": 8.369, "count": 43, "high": 8.395, "id": 1579996860, "low": 8.361, "open": 8.379, "vol": 2306}, {"amount": 145.71278031629353, "close": 8.374, "count": 9, "high": 8.384, "id": 1579996920, "low": 8.36, "open": 8.361, "vol": 122}, {"amount": 197.66474519137188, "close": 8.399, "count": 6, "high": 8.403, "id": 1579996980, "low": 8.391, "open": 8.391, "vol": 166}, {"amount": 2454.8405214368195, "close": 8.392, "count": 6, "high": 8.401, "id": 1579997040, "low": 8.389, "open": 8.4, "vol": 2062}, {"amount": 2493.193174433255, "close": 8.388, "count": 22, "high": 8.391, "id": 1579997100, "low": 8.384, "open": 8.385, "vol": 2092}, {"amount": 109.65662455150618, "close": 8.387, "count": 3, "high": 8.39, "id": 1579997160, "low": 8.385, "open": 8.385, "vol": 92}, {"amount": 2890.477079644961, "close": 8.37, "count": 13, "high": 8.375, "id": 1579997220, "low": 8.37, "open": 8.375, "vol": 2420}, {"amount": 3281.878726038517, "close": 8.389, "count": 11, "high": 8.389, "id": 1579997280, "low": 8.372, "open": 8.373, "vol": 2748}, {"amount": 126.45578016115724, "close": 8.375, "count": 4, "high": 8.387, "id": 1579997340, "low": 8.375, "open": 8.387, "vol": 106}, {"amount": 4764.783578703912, "close": 8.371, "count": 29, "high": 8.371, "id": 1579997400, "low": 8.364, "open": 8.37, "vol": 3988}, {"amount": 1291.8203681980137, "close": 8.384, "count": 8, "high": 8.384, "id": 1579997460, "low": 8.37, "open": 8.37, "vol": 1082}, {"amount": 470.3511287674768, "close": 8.378, "count": 5, "high": 8.379, "id": 1579997520, "low": 8.376, "open": 8.376, "vol": 394}, {"amount": 295.76283693509595, "close": 8.385, "count": 3, "high": 8.386, "id": 1579997580, "low": 8.383, "open": 8.386, "vol": 248}, {"amount": 367.32004735687764, "close": 8.382, "count": 5, "high": 8.389, "id": 1579997640, "low": 8.382, "open": 8.385, "vol": 308}, {"amount": 2.3860653781913626, "close": 8.382, "count": 1, "high": 8.382, "id": 1579997700, "low": 8.382, "open": 8.382, "vol": 2}, {"amount": 715.5592428952161, "close": 8.384, "count": 8, "high": 8.39, "id": 1579997760, "low": 8.384, "open": 8.39, "vol": 600}, {"amount": 1482.5454042393303, "close": 8.372, "count": 9, "high": 8.384, "id": 1579997820, "low": 8.372, "open": 8.38, "vol": 1242}, {"amount": 15601.462169287925, "close": 8.296, "count": 85, "high": 8.367, "id": 1579997880, "low": 8.287, "open": 8.36, "vol": 12990}, {"amount": 11224.249867921655, "close": 8.301, "count": 63, "high": 8.338, "id": 1579997940, "low": 8.276, "open": 8.3, "vol": 9322}, {"amount": 1107.8858370786234, "close": 8.31, "count": 21, "high": 8.315, "id": 1579998000, "low": 8.293, "open": 8.313, "vol": 920}, {"amount": 378.7347563731985, "close": 8.288, "count": 9, "high": 8.297, "id": 1579998060, "low": 8.288, "open": 8.293, "vol": 314}, {"amount": 1334.2660347586136, "close": 8.256, "count": 11, "high": 8.288, "id": 1579998120, "low": 8.256, "open": 8.288, "vol": 1104}, {"amount": 1923.9332671529842, "close": 8.277, "count": 11, "high": 8.277, "id": 1579998180, "low": 8.256, "open": 8.256, "vol": 1590}, {"amount": 3331.023803303702, "close": 8.261, "count": 16, "high": 8.272, "id": 1579998240, "low": 8.261, "open": 8.269, "vol": 2754}, {"amount": 3514.0007821682343, "close": 8.261, "count": 23, "high": 8.282, "id": 1579998300, "low": 8.25, "open": 8.27, "vol": 2902}, {"amount": 1877.1220573566543, "close": 8.251, "count": 10, "high": 8.269, "id": 1579998360, "low": 8.251, "open": 8.263, "vol": 1552}, {"amount": 1362.8007979086622, "close": 8.277, "count": 14, "high": 8.292, "id": 1579998420, "low": 8.255, "open": 8.265, "vol": 1128}, {"amount": 298.5211568714001, "close": 8.302, "count": 7, "high": 8.309, "id": 1579998480, "low": 8.29, "open": 8.291, "vol": 248}, {"amount": 2590.160196622985, "close": 8.304, "count": 16, "high": 8.321, "id": 1579998540, "low": 8.293, "open": 8.306, "vol": 2152}, {"amount": 180.64280200241717, "close": 8.307, "count": 4, "high": 8.307, "id": 1579998600, "low": 8.303, "open": 8.304, "vol": 150}, {"amount": 1824.895112580982, "close": 8.339, "count": 13, "high": 8.349, "id": 1579998660, "low": 8.317, "open": 8.317, "vol": 1520}, {"amount": 2528.855288827805, "close": 8.333, "count": 13, "high": 8.34, "id": 1579998720, "low": 8.329, "open": 8.329, "vol": 2108}, {"amount": 2143.375945075461, "close": 8.344, "count": 9, "high": 8.347, "id": 1579998780, "low": 8.339, "open": 8.34, "vol": 1788}, {"amount": 2813.3875483834886, "close": 8.348, "count": 16, "high": 8.35, "id": 1579998840, "low": 8.339, "open": 8.344, "vol": 2348}, {"amount": 1672.541302645458, "close": 8.337, "count": 13, "high": 8.35, "id": 1579998900, "low": 8.337, "open": 8.348, "vol": 1396}, {"amount": 342.5529151160732, "close": 8.35, "count": 6, "high": 8.353, "id": 1579998960, "low": 8.34, "open": 8.34, "vol": 286}, {"amount": 506.75566564895604, "close": 8.313, "count": 9, "high": 8.345, "id": 1579999020, "low": 8.313, "open": 8.345, "vol": 422}, {"amount": 4195.881430456142, "close": 8.321, "count": 22, "high": 8.328, "id": 1579999080, "low": 8.309, "open": 8.315, "vol": 3488}, {"amount": 545.135951216967, "close": 8.325, "count": 4, "high": 8.329, "id": 1579999140, "low": 8.323, "open": 8.323, "vol": 454}, {"amount": 76.76939280185465, "close": 8.336, "count": 2, "high": 8.343, "id": 1579999200, "low": 8.336, "open": 8.343, "vol": 64}, {"amount": 103.20096326290586, "close": 8.335, "count": 4, "high": 8.34, "id": 1579999260, "low": 8.332, "open": 8.34, "vol": 86}, {"amount": 4.799616030717543, "close": 8.334, "count": 1, "high": 8.334, "id": 1579999320, "low": 8.334, "open": 8.334, "vol": 4}, {"amount": 4.802497298595269, "close": 8.329, "count": 1, "high": 8.329, "id": 1579999380, "low": 8.329, "open": 8.329, "vol": 4}, {"amount": 76.90343565784177, "close": 8.322, "count": 2, "high": 8.326, "id": 1579999440, "low": 8.322, "open": 8.326, "vol": 64}, {"amount": 1862.4911962651818, "close": 8.322, "count": 5, "high": 8.327, "id": 1579999500, "low": 8.322, "open": 8.322, "vol": 1550}, {"amount": 7.202593579347197, "close": 8.331, "count": 3, "high": 8.333, "id": 1579999560, "low": 8.327, "open": 8.327, "vol": 6}, {"amount": 11.983223487118035, "close": 8.345, "count": 1, "high": 8.345, "id": 1579999620, "low": 8.345, "open": 8.345, "vol": 10}, {"amount": 2912.2417242719316, "close": 8.361, "count": 22, "high": 8.372, "id": 1579999680, "low": 8.348, "open": 8.348, "vol": 2434}, {"amount": 2.390343014222541, "close": 8.367, "count": 1, "high": 8.367, "id": 1579999740, "low": 8.367, "open": 8.367, "vol": 2}, {"amount": 650.212163133031, "close": 8.368, "count": 4, "high": 8.368, "id": 1579999800, "low": 8.364, "open": 8.364, "vol": 544}, {"amount": 4457.627977138343, "close": 8.368, "count": 18, "high": 8.374, "id": 1579999860, "low": 8.361, "open": 8.373, "vol": 3730}, {"amount": 9.563658099222954, "close": 8.365, "count": 1, "high": 8.365, "id": 1579999920, "low": 8.365, "open": 8.365, "vol": 8}, {"amount": 948.5325339429368, "close": 8.371, "count": 9, "high": 8.374, "id": 1579999980, "low": 8.367, "open": 8.367, "vol": 794}, {"amount": 2716.7522877675933, "close": 8.372, "count": 11, "high": 8.373, "id": 1580000040, "low": 8.362, "open": 8.373, "vol": 2274}, {"amount": 2909.737252344382, "close": 8.358, "count": 8, "high": 8.369, "id": 1580000100, "low": 8.358, "open": 8.369, "vol": 2434}, {"amount": 5155.168760402807, "close": 8.353, "count": 22, "high": 8.359, "id": 1580000160, "low": 8.346, "open": 8.351, "vol": 4306}, {"amount": 1872.0006397090092, "close": 8.351, "count": 17, "high": 8.358, "id": 1580000220, "low": 8.348, "open": 8.35, "vol": 1564}, {"amount": 117.43472869111928, "close": 8.346, "count": 3, "high": 8.346, "id": 1580000280, "low": 8.345, "open": 8.345, "vol": 98}, {"amount": 4.791566842357451, "close": 8.348, "count": 2, "high": 8.348, "id": 1580000340, "low": 8.348, "open": 8.348, "vol": 4}, {"amount": 323.60707101420337, "close": 8.343, "count": 5, "high": 8.345, "id": 1580000400, "low": 8.343, "open": 8.344, "vol": 270}, {"amount": 4346.488684214039, "close": 8.357, "count": 20, "high": 8.357, "id": 1580000460, "low": 8.336, "open": 8.336, "vol": 3630}, {"amount": 177.10599072169072, "close": 8.368, "count": 7, "high": 8.368, "id": 1580000520, "low": 8.351, "open": 8.351, "vol": 148}, {"amount": 1129.0566218999195, "close": 8.377, "count": 11, "high": 8.38, "id": 1580000580, "low": 8.376, "open": 8.376, "vol": 946}, {"amount": 3280.0244358746054, "close": 8.393, "count": 19, "high": 8.393, "id": 1580000640, "low": 8.373, "open": 8.376, "vol": 2750}, {"amount": 1434.6683191764628, "close": 8.393, "count": 11, "high": 8.395, "id": 1580000700, "low": 8.385, "open": 8.395, "vol": 1204}, {"amount": 6475.193156073167, "close": 8.373, "count": 25, "high": 8.401, "id": 1580000760, "low": 8.373, "open": 8.396, "vol": 5436}, {"amount": 1107.325954868615, "close": 8.381, "count": 13, "high": 8.382, "id": 1580000820, "low": 8.379, "open": 8.379, "vol": 928}, {"amount": 324.22561477512664, "close": 8.393, "count": 8, "high": 8.393, "id": 1580000880, "low": 8.385, "open": 8.385, "vol": 272}, {"amount": 397.8808455697823, "close": 8.395, "count": 3, "high": 8.395, "id": 1580000940, "low": 8.393, "open": 8.393, "vol": 334}, {"amount": 7802.217311283842, "close": 8.397, "count": 9, "high": 8.401, "id": 1580001000, "low": 8.394, "open": 8.394, "vol": 6550}, {"amount": 14972.732629014556, "close": 8.413, "count": 47, "high": 8.418, "id": 1580001060, "low": 8.395, "open": 8.395, "vol": 12584}, {"amount": 948.5614741277668, "close": 8.39, "count": 10, "high": 8.408, "id": 1580001120, "low": 8.387, "open": 8.408, "vol": 796}, {"amount": 3084.349613884834, "close": 8.389, "count": 22, "high": 8.401, "id": 1580001180, "low": 8.379, "open": 8.4, "vol": 2586}, {"amount": 2628.694846343948, "close": 8.392, "count": 5, "high": 8.392, "id": 1580001240, "low": 8.391, "open": 8.392, "vol": 2206}, {"amount": 407.1420443988799, "close": 8.399, "count": 8, "high": 8.402, "id": 1580001300, "low": 8.385, "open": 8.385, "vol": 342}, {"amount": 2186.182497234905, "close": 8.398, "count": 15, "high": 8.402, "id": 1580001360, "low": 8.396, "open": 8.396, "vol": 1836}, {"amount": 485.53861284208926, "close": 8.405, "count": 2, "high": 8.405, "id": 1580001420, "low": 8.403, "open": 8.403, "vol": 408}, {"amount": 964.719330148829, "close": 8.397, "count": 9, "high": 8.4, "id": 1580001480, "low": 8.393, "open": 8.4, "vol": 810}, {"amount": 4444.426968481292, "close": 8.388, "count": 20, "high": 8.395, "id": 1580001540, "low": 8.388, "open": 8.395, "vol": 3730}, {"amount": 2222.698058757131, "close": 8.377, "count": 21, "high": 8.393, "id": 1580001600, "low": 8.377, "open": 8.389, "vol": 1864}, {"amount": 813.7246129588992, "close": 8.382, "count": 6, "high": 8.384, "id": 1580001660, "low": 8.379, "open": 8.384, "vol": 682}, {"amount": 1394.6497804002995, "close": 8.384, "count": 10, "high": 8.391, "id": 1580001720, "low": 8.381, "open": 8.381, "vol": 1170}, {"amount": 4245.522460692055, "close": 8.401, "count": 19, "high": 8.401, "id": 1580001780, "low": 8.386, "open": 8.386, "vol": 3564}, {"amount": 3701.296577940114, "close": 8.411, "count": 12, "high": 8.418, "id": 1580001840, "low": 8.403, "open": 8.404, "vol": 3112}, {"amount": 9.517011658339282, "close": 8.406, "count": 1, "high": 8.406, "id": 1580001900, "low": 8.406, "open": 8.406, "vol": 8}, {"amount": 178.69113021141288, "close": 8.396, "count": 4, "high": 8.396, "id": 1580001960, "low": 8.391, "open": 8.391, "vol": 150}, {"amount": 4.7647409172126265, "close": 8.395, "count": 1, "high": 8.395, "id": 1580002020, "low": 8.395, "open": 8.395, "vol": 4}, {"amount": 3170.1275647749294, "close": 8.378, "count": 9, "high": 8.388, "id": 1580002080, "low": 8.377, "open": 8.387, "vol": 2658}, {"amount": 924.0830445135565, "close": 8.38, "count": 5, "high": 8.38, "id": 1580002140, "low": 8.375, "open": 8.378, "vol": 774}, {"amount": 23.86635388642213, "close": 8.384, "count": 2, "high": 8.384, "id": 1580002200, "low": 8.376, "open": 8.376, "vol": 20}, {"amount": 2722.363262227659, "close": 8.385, "count": 17, "high": 8.39, "id": 1580002260, "low": 8.379, "open": 8.379, "vol": 2282}, {"amount": 848.8678000081579, "close": 8.389, "count": 10, "high": 8.394, "id": 1580002320, "low": 8.387, "open": 8.389, "vol": 712}, {"amount": 154.8997831389974, "close": 8.392, "count": 4, "high": 8.393, "id": 1580002380, "low": 8.392, "open": 8.393, "vol": 130}, {"amount": 248.03301098384355, "close": 8.385, "count": 3, "high": 8.392, "id": 1580002440, "low": 8.385, "open": 8.392, "vol": 208}, {"amount": 186.0943397535183, "close": 8.385, "count": 8, "high": 8.389, "id": 1580002500, "low": 8.379, "open": 8.384, "vol": 156}, {"amount": 307.79958781175947, "close": 8.382, "count": 2, "high": 8.384, "id": 1580002560, "low": 8.382, "open": 8.384, "vol": 258}, {"amount": 38.138378227987786, "close": 8.393, "count": 2, "high": 8.393, "id": 1580002620, "low": 8.385, "open": 8.385, "vol": 32}, {"amount": 2624.5459421212813, "close": 8.393, "count": 7, "high": 8.393, "id": 1580002680, "low": 8.387, "open": 8.389, "vol": 2202}, {"amount": 247.7971803374614, "close": 8.394, "count": 2, "high": 8.394, "id": 1580002740, "low": 8.393, "open": 8.393, "vol": 208}, {"amount": 3646.0784631156284, "close": 8.397, "count": 12, "high": 8.399, "id": 1580002800, "low": 8.395, "open": 8.398, "vol": 3062}, {"amount": 114.35633698618781, "close": 8.395, "count": 2, "high": 8.395, "id": 1580002860, "low": 8.392, "open": 8.392, "vol": 96}, {"amount": 123.89887425761408, "close": 8.391, "count": 2, "high": 8.394, "id": 1580002920, "low": 8.391, "open": 8.394, "vol": 104}, {"amount": 1280.059559383728, "close": 8.39, "count": 8, "high": 8.391, "id": 1580002980, "low": 8.389, "open": 8.39, "vol": 1074}, {"amount": 1119.8551762633247, "close": 8.394, "count": 6, "high": 8.394, "id": 1580003040, "low": 8.39, "open": 8.39, "vol": 940}, {"amount": 140.6095375638045, "close": 8.391, "count": 4, "high": 8.393, "id": 1580003100, "low": 8.391, "open": 8.391, "vol": 118}, {"amount": 4844.127462068805, "close": 8.407, "count": 13, "high": 8.407, "id": 1580003160, "low": 8.393, "open": 8.393, "vol": 4072}, {"amount": 16721.825036261023, "close": 8.413, "count": 66, "high": 8.448, "id": 1580003220, "low": 8.408, "open": 8.413, "vol": 14092}, {"amount": 29020.82429125326, "close": 8.425, "count": 70, "high": 8.45, "id": 1580003280, "low": 8.407, "open": 8.407, "vol": 24476}, {"amount": 2064.547299040112, "close": 8.42, "count": 35, "high": 8.424, "id": 1580003340, "low": 8.412, "open": 8.424, "vol": 1738}, {"amount": 306.5072840910976, "close": 8.415, "count": 4, "high": 8.419, "id": 1580003400, "low": 8.415, "open": 8.419, "vol": 258}, {"amount": 724.8579039358413, "close": 8.411, "count": 5, "high": 8.416, "id": 1580003460, "low": 8.411, "open": 8.416, "vol": 610}, {"amount": 5176.477082240522, "close": 8.398, "count": 14, "high": 8.408, "id": 1580003520, "low": 8.398, "open": 8.408, "vol": 4352}, {"amount": 268.76618572327493, "close": 8.412, "count": 9, "high": 8.412, "id": 1580003580, "low": 8.405, "open": 8.405, "vol": 226}, {"amount": 1825.4422968143062, "close": 8.403, "count": 12, "high": 8.409, "id": 1580003640, "low": 8.402, "open": 8.408, "vol": 1534}, {"amount": 2335.937805605551, "close": 8.402, "count": 25, "high": 8.404, "id": 1580003700, "low": 8.393, "open": 8.403, "vol": 1962}, {"amount": 361.90362838779885, "close": 8.402, "count": 2, "high": 8.402, "id": 1580003760, "low": 8.4, "open": 8.4, "vol": 304}, {"amount": 670.7224045170152, "close": 8.409, "count": 3, "high": 8.409, "id": 1580003820, "low": 8.405, "open": 8.405, "vol": 564}, {"amount": 135.52775234749728, "close": 8.41, "count": 6, "high": 8.413, "id": 1580003880, "low": 8.41, "open": 8.411, "vol": 114}, {"amount": 6222.457295349523, "close": 8.41, "count": 8, "high": 8.412, "id": 1580003940, "low": 8.408, "open": 8.411, "vol": 5234}, {"amount": 2105.5425673036284, "close": 8.394, "count": 22, "high": 8.41, "id": 1580004000, "low": 8.394, "open": 8.409, "vol": 1770}, {"amount": 216.78691600388382, "close": 8.397, "count": 6, "high": 8.397, "id": 1580004060, "low": 8.393, "open": 8.393, "vol": 182}, {"amount": 1506.2225566483087, "close": 8.391, "count": 15, "high": 8.396, "id": 1580004120, "low": 8.39, "open": 8.391, "vol": 1264}, {"amount": 15627.02924555019, "close": 8.383, "count": 17, "high": 8.39, "id": 1580004180, "low": 8.383, "open": 8.39, "vol": 13108}, {"amount": 679.5383272172764, "close": 8.389, "count": 11, "high": 8.395, "id": 1580004240, "low": 8.382, "open": 8.384, "vol": 570}, {"amount": 217.07617020734304, "close": 8.386, "count": 5, "high": 8.386, "id": 1580004300, "low": 8.384, "open": 8.386, "vol": 182}, {"amount": 78.72507398302541, "close": 8.383, "count": 4, "high": 8.384, "id": 1580004360, "low": 8.381, "open": 8.384, "vol": 66}, {"amount": 689.9289225914196, "close": 8.379, "count": 12, "high": 8.383, "id": 1580004420, "low": 8.377, "open": 8.383, "vol": 578}, {"amount": 861.550164878133, "close": 8.382, "count": 4, "high": 8.382, "id": 1580004480, "low": 8.378, "open": 8.378, "vol": 722}, {"amount": 3511.8107177350644, "close": 8.395, "count": 20, "high": 8.4, "id": 1580004540, "low": 8.381, "open": 8.383, "vol": 2946}, {"amount": 738.4642761184951, "close": 8.399, "count": 5, "high": 8.399, "id": 1580004600, "low": 8.391, "open": 8.393, "vol": 620}, {"amount": 78.6463298379409, "close": 8.392, "count": 2, "high": 8.392, "id": 1580004660, "low": 8.392, "open": 8.392, "vol": 66}, {"amount": 9.536866049088026, "close": 8.389, "count": 2, "high": 8.389, "id": 1580004720, "low": 8.387, "open": 8.387, "vol": 8}, {"amount": 11.920371915603766, "close": 8.389, "count": 1, "high": 8.389, "id": 1580004780, "low": 8.389, "open": 8.389, "vol": 10}, {"amount": 97.7811647718639, "close": 8.389, "count": 2, "high": 8.389, "id": 1580004840, "low": 8.386, "open": 8.386, "vol": 82}, {"amount": 1125.8281812098253, "close": 8.383, "count": 6, "high": 8.386, "id": 1580004900, "low": 8.383, "open": 8.386, "vol": 944}, {"amount": 9.53970917452607, "close": 8.387, "count": 2, "high": 8.387, "id": 1580004960, "low": 8.385, "open": 8.385, "vol": 8}, {"amount": 76.29038025986411, "close": 8.389, "count": 2, "high": 8.389, "id": 1580005020, "low": 8.389, "open": 8.389, "vol": 64}, {"amount": 4.767580452920143, "close": 8.39, "count": 1, "high": 8.39, "id": 1580005080, "low": 8.39, "open": 8.39, "vol": 4}, {"amount": 390.8004392623157, "close": 8.394, "count": 4, "high": 8.394, "id": 1580005140, "low": 8.393, "open": 8.393, "vol": 328}, {"amount": 88.19541089953456, "close": 8.387, "count": 2, "high": 8.391, "id": 1580005200, "low": 8.387, "open": 8.391, "vol": 74}, {"amount": 888.2793159413917, "close": 8.375, "count": 8, "high": 8.382, "id": 1580005260, "low": 8.373, "open": 8.382, "vol": 744}, {"amount": 11.938019146059476, "close": 8.371, "count": 2, "high": 8.378, "id": 1580005320, "low": 8.371, "open": 8.378, "vol": 10}, {"amount": 609.316427996286, "close": 8.37, "count": 3, "high": 8.373, "id": 1580005380, "low": 8.37, "open": 8.373, "vol": 510}, {"amount": 2807.4066208010145, "close": 8.367, "count": 14, "high": 8.376, "id": 1580005440, "low": 8.367, "open": 8.367, "vol": 2350}, {"amount": 849.3779070571894, "close": 8.359, "count": 8, "high": 8.362, "id": 1580005500, "low": 8.356, "open": 8.362, "vol": 710}, {"amount": 688.9329724965587, "close": 8.355, "count": 8, "high": 8.364, "id": 1580005560, "low": 8.355, "open": 8.364, "vol": 576}, {"amount": 787.5755906597894, "close": 8.361, "count": 5, "high": 8.361, "id": 1580005620, "low": 8.354, "open": 8.355, "vol": 658}, {"amount": 7256.796408343525, "close": 8.355, "count": 7, "high": 8.365, "id": 1580005680, "low": 8.355, "open": 8.365, "vol": 6064}, {"amount": 2755.1803618594495, "close": 8.35, "count": 8, "high": 8.35, "id": 1580005740, "low": 8.346, "open": 8.35, "vol": 2300}, {"amount": 9.576250897773521, "close": 8.354, "count": 1, "high": 8.354, "id": 1580005800, "low": 8.354, "open": 8.354, "vol": 8}, {"amount": 4.790132481968382, "close": 8.352, "count": 2, "high": 8.352, "id": 1580005860, "low": 8.349, "open": 8.349, "vol": 4}, {"amount": 4.784688995215311, "close": 8.36, "count": 1, "high": 8.36, "id": 1580005920, "low": 8.36, "open": 8.36, "vol": 4}, {"amount": 177.13256619978583, "close": 8.355, "count": 2, "high": 8.361, "id": 1580005980, "low": 8.355, "open": 8.361, "vol": 148}, {"amount": 2.3932033026205577, "close": 8.357, "count": 1, "high": 8.357, "id": 1580006040, "low": 8.357, "open": 8.357, "vol": 2}, {"amount": 1198.724606471004, "close": 8.359, "count": 7, "high": 8.364, "id": 1580006100, "low": 8.355, "open": 8.355, "vol": 1002}, {"amount": 14.343772412144395, "close": 8.366, "count": 2, "high": 8.366, "id": 1580006160, "low": 8.366, "open": 8.366, "vol": 12}, {"amount": 377.68507113706835, "close": 8.368, "count": 4, "high": 8.368, "id": 1580006220, "low": 8.364, "open": 8.364, "vol": 316}], "status": "ok", "ts": 1580006276616}