{"ch": "market.TRX_CW.kline.1min", "data": [{"amount": 0, "close": 0.01166, "count": 0, "high": 0.01166, "id": 1585261560, "low": 0.01166, "open": 0.01166, "vol": 0}, {"amount": 0, "close": 0.01166, "count": 0, "high": 0.01166, "id": 1585261620, "low": 0.01166, "open": 0.01166, "vol": 0}, {"amount": 0, "close": 0.01166, "count": 0, "high": 0.01166, "id": 1585261680, "low": 0.01166, "open": 0.01166, "vol": 0}, {"amount": 0, "close": 0.01166, "count": 0, "high": 0.01166, "id": 1585261740, "low": 0.01166, "open": 0.01166, "vol": 0}, {"amount": 0, "close": 0.01166, "count": 0, "high": 0.01166, "id": 1585261800, "low": 0.01166, "open": 0.01166, "vol": 0}, {"amount": 0, "close": 0.01166, "count": 0, "high": 0.01166, "id": 1585261860, "low": 0.01166, "open": 0.01166, "vol": 0}, {"amount": 0, "close": 0.01166, "count": 0, "high": 0.01166, "id": 1585261920, "low": 0.01166, "open": 0.01166, "vol": 0}, {"amount": 0, "close": 0.01166, "count": 0, "high": 0.01166, "id": 1585261980, "low": 0.01166, "open": 0.01166, "vol": 0}, {"amount": 0, "close": 0.01166, "count": 0, "high": 0.01166, "id": 1585262040, "low": 0.01166, "open": 0.01166, "vol": 0}, {"amount": 0, "close": 0.01166, "count": 0, "high": 0.01166, "id": 1585262100, "low": 0.01166, "open": 0.01166, "vol": 0}, {"amount": 0, "close": 0.01166, "count": 0, "high": 0.01166, "id": 1585262160, "low": 0.01166, "open": 0.01166, "vol": 0}, {"amount": 0, "close": 0.01166, "count": 0, "high": 0.01166, "id": 1585262220, "low": 0.01166, "open": 0.01166, "vol": 0}, {"amount": 0, "close": 0.01166, "count": 0, "high": 0.01166, "id": 1585262280, "low": 0.01166, "open": 0.01166, "vol": 0}, {"amount": 0, "close": 0.01166, "count": 0, "high": 0.01166, "id": 1585262340, "low": 0.01166, "open": 0.01166, "vol": 0}, {"amount": 0, "close": 0.01166, "count": 0, "high": 0.01166, "id": 1585262400, "low": 0.01166, "open": 0.01166, "vol": 0}, {"amount": 0, "close": 0.01166, "count": 0, "high": 0.01166, "id": 1585262460, "low": 0.01166, "open": 0.01166, "vol": 0}, {"amount": 116338.75106929, "close": 0.01169, "count": 3, "high": 0.01169, "id": 1585262520, "low": 0.01169, "open": 0.01169, "vol": 136}, {"amount": 0, "close": 0.01169, "count": 0, "high": 0.01169, "id": 1585262580, "low": 0.01169, "open": 0.01169, "vol": 0}, {"amount": 0, "close": 0.01169, "count": 0, "high": 0.01169, "id": 1585262640, "low": 0.01169, "open": 0.01169, "vol": 0}, {"amount": 0, "close": 0.01169, "count": 0, "high": 0.01169, "id": 1585262700, "low": 0.01169, "open": 0.01169, "vol": 0}, {"amount": 0, "close": 0.01169, "count": 0, "high": 0.01169, "id": 1585262760, "low": 0.01169, "open": 0.01169, "vol": 0}, {"amount": 0, "close": 0.01169, "count": 0, "high": 0.01169, "id": 1585262820, "low": 0.01169, "open": 0.01169, "vol": 0}, {"amount": 0, "close": 0.01169, "count": 0, "high": 0.01169, "id": 1585262880, "low": 0.01169, "open": 0.01169, "vol": 0}, {"amount": 0, "close": 0.01169, "count": 0, "high": 0.01169, "id": 1585262940, "low": 0.01169, "open": 0.01169, "vol": 0}, {"amount": 0, "close": 0.01169, "count": 0, "high": 0.01169, "id": 1585263000, "low": 0.01169, "open": 0.01169, "vol": 0}, {"amount": 10247.651579846286, "close": 0.01171, "count": 1, "high": 0.01171, "id": 1585263060, "low": 0.01171, "open": 0.01171, "vol": 12}, {"amount": 13663.535439795047, "close": 0.01171, "count": 2, "high": 0.01171, "id": 1585263120, "low": 0.01171, "open": 0.01171, "vol": 16}, {"amount": 0, "close": 0.01171, "count": 0, "high": 0.01171, "id": 1585263180, "low": 0.01171, "open": 0.01171, "vol": 0}, {"amount": 5132.591958939264, "close": 0.01169, "count": 1, "high": 0.01169, "id": 1585263240, "low": 0.01169, "open": 0.01169, "vol": 6}, {"amount": 34217.27972626176, "close": 0.01169, "count": 1, "high": 0.01169, "id": 1585263300, "low": 0.01169, "open": 0.01169, "vol": 40}, {"amount": 0, "close": 0.01169, "count": 0, "high": 0.01169, "id": 1585263360, "low": 0.01169, "open": 0.01169, "vol": 0}, {"amount": 0, "close": 0.01169, "count": 0, "high": 0.01169, "id": 1585263420, "low": 0.01169, "open": 0.01169, "vol": 0}, {"amount": 0, "close": 0.01169, "count": 0, "high": 0.01169, "id": 1585263480, "low": 0.01169, "open": 0.01169, "vol": 0}, {"amount": 0, "close": 0.01169, "count": 0, "high": 0.01169, "id": 1585263540, "low": 0.01169, "open": 0.01169, "vol": 0}, {"amount": 320033.34662365436, "close": 0.01175, "count": 2, "high": 0.01175, "id": 1585263600, "low": 0.01174, "open": 0.01174, "vol": 376}, {"amount": 0, "close": 0.01175, "count": 0, "high": 0.01175, "id": 1585263660, "low": 0.01175, "open": 0.01175, "vol": 0}, {"amount": 119047.61904761905, "close": 0.01176, "count": 2, "high": 0.01176, "id": 1585263720, "low": 0.01176, "open": 0.01176, "vol": 140}, {"amount": 52631.57894736842, "close": 0.01178, "count": 1, "high": 0.01178, "id": 1585263780, "low": 0.01178, "open": 0.01178, "vol": 62}, {"amount": 0, "close": 0.01178, "count": 0, "high": 0.01178, "id": 1585263840, "low": 0.01178, "open": 0.01178, "vol": 0}, {"amount": 269949.0662139219, "close": 0.01178, "count": 2, "high": 0.01178, "id": 1585263900, "low": 0.01178, "open": 0.01178, "vol": 318}, {"amount": 0, "close": 0.01178, "count": 0, "high": 0.01178, "id": 1585263960, "low": 0.01178, "open": 0.01178, "vol": 0}, {"amount": 150860.79000919304, "close": 0.01183, "count": 4, "high": 0.01183, "id": 1585264020, "low": 0.01178, "open": 0.01178, "vol": 178}, {"amount": 0, "close": 0.01183, "count": 0, "high": 0.01183, "id": 1585264080, "low": 0.01183, "open": 0.01183, "vol": 0}, {"amount": 53923.12161968259, "close": 0.01187, "count": 6, "high": 0.01187, "id": 1585264140, "low": 0.01186, "open": 0.01186, "vol": 64}, {"amount": 32013.479359730412, "close": 0.01187, "count": 5, "high": 0.01187, "id": 1585264200, "low": 0.01187, "open": 0.01187, "vol": 38}, {"amount": 67226.89075630253, "close": 0.0119, "count": 2, "high": 0.0119, "id": 1585264260, "low": 0.0119, "open": 0.0119, "vol": 80}, {"amount": 0, "close": 0.0119, "count": 0, "high": 0.0119, "id": 1585264320, "low": 0.0119, "open": 0.0119, "vol": 0}, {"amount": 26914.78847912826, "close": 0.01189, "count": 3, "high": 0.01189, "id": 1585264380, "low": 0.01188, "open": 0.01188, "vol": 32}, {"amount": 0, "close": 0.01189, "count": 0, "high": 0.01189, "id": 1585264440, "low": 0.01189, "open": 0.01189, "vol": 0}, {"amount": 2799831.499592157, "close": 0.01193, "count": 21, "high": 0.01195, "id": 1585264500, "low": 0.01189, "open": 0.01189, "vol": 3338}, {"amount": 3350.0837520938026, "close": 0.01194, "count": 1, "high": 0.01194, "id": 1585264560, "low": 0.01194, "open": 0.01194, "vol": 4}, {"amount": 0, "close": 0.01194, "count": 0, "high": 0.01194, "id": 1585264620, "low": 0.01194, "open": 0.01194, "vol": 0}, {"amount": 63397.32203614588, "close": 0.01199, "count": 3, "high": 0.01199, "id": 1585264680, "low": 0.01195, "open": 0.01195, "vol": 76}, {"amount": 0, "close": 0.01199, "count": 0, "high": 0.01199, "id": 1585264740, "low": 0.01199, "open": 0.01199, "vol": 0}, {"amount": 0, "close": 0.01199, "count": 0, "high": 0.01199, "id": 1585264800, "low": 0.01199, "open": 0.01199, "vol": 0}, {"amount": 8354.21888053467, "close": 0.01197, "count": 2, "high": 0.01197, "id": 1585264860, "low": 0.01197, "open": 0.01197, "vol": 10}, {"amount": 156947.75573559053, "close": 0.01196, "count": 5, "high": 0.01198, "id": 1585264920, "low": 0.01196, "open": 0.01198, "vol": 188}, {"amount": 11705.685618729098, "close": 0.01196, "count": 3, "high": 0.01196, "id": 1585264980, "low": 0.01196, "open": 0.01196, "vol": 14}, {"amount": 118902.74244303806, "close": 0.01194, "count": 2, "high": 0.01195, "id": 1585265040, "low": 0.01194, "open": 0.01195, "vol": 142}, {"amount": 3350.0837520938026, "close": 0.01194, "count": 1, "high": 0.01194, "id": 1585265100, "low": 0.01194, "open": 0.01194, "vol": 4}, {"amount": 879367.5631062492, "close": 0.01196, "count": 10, "high": 0.01196, "id": 1585265160, "low": 0.01194, "open": 0.01194, "vol": 1050}, {"amount": 0, "close": 0.01196, "count": 0, "high": 0.01196, "id": 1585265220, "low": 0.01196, "open": 0.01196, "vol": 0}, {"amount": 0, "close": 0.01196, "count": 0, "high": 0.01196, "id": 1585265280, "low": 0.01196, "open": 0.01196, "vol": 0}, {"amount": 640345.4987572092, "close": 0.012, "count": 11, "high": 0.012, "id": 1585265340, "low": 0.01196, "open": 0.01199, "vol": 766}, {"amount": 0, "close": 0.012, "count": 0, "high": 0.012, "id": 1585265400, "low": 0.012, "open": 0.012, "vol": 0}, {"amount": 589456.0966249701, "close": 0.01201, "count": 4, "high": 0.01202, "id": 1585265460, "low": 0.01201, "open": 0.01202, "vol": 708}, {"amount": 0, "close": 0.01201, "count": 0, "high": 0.01201, "id": 1585265520, "low": 0.01201, "open": 0.01201, "vol": 0}, {"amount": 441322.1482346999, "close": 0.01191, "count": 9, "high": 0.01194, "id": 1585265580, "low": 0.01191, "open": 0.01194, "vol": 526}, {"amount": 1394620.54877672, "close": 0.0119, "count": 12, "high": 0.01191, "id": 1585265640, "low": 0.01188, "open": 0.01191, "vol": 1660}, {"amount": 1589915.9663865545, "close": 0.0119, "count": 6, "high": 0.0119, "id": 1585265700, "low": 0.0119, "open": 0.0119, "vol": 1892}, {"amount": 30226.700251889168, "close": 0.01191, "count": 1, "high": 0.01191, "id": 1585265760, "low": 0.01191, "open": 0.01191, "vol": 36}, {"amount": 3358.5222502099077, "close": 0.01191, "count": 1, "high": 0.01191, "id": 1585265820, "low": 0.01191, "open": 0.01191, "vol": 4}, {"amount": 210216.94708925698, "close": 0.01189, "count": 12, "high": 0.0119, "id": 1585265880, "low": 0.01188, "open": 0.0119, "vol": 250}, {"amount": 95850.61947403014, "close": 0.0119, "count": 4, "high": 0.0119, "id": 1585265940, "low": 0.01189, "open": 0.01189, "vol": 114}, {"amount": 0, "close": 0.0119, "count": 0, "high": 0.0119, "id": 1585266000, "low": 0.0119, "open": 0.0119, "vol": 0}, {"amount": 0, "close": 0.0119, "count": 0, "high": 0.0119, "id": 1585266060, "low": 0.0119, "open": 0.0119, "vol": 0}, {"amount": 683536.8979478545, "close": 0.0119, "count": 10, "high": 0.01191, "id": 1585266120, "low": 0.01189, "open": 0.01189, "vol": 814}, {"amount": 199664.42953020133, "close": 0.01192, "count": 5, "high": 0.01192, "id": 1585266180, "low": 0.01192, "open": 0.01192, "vol": 238}, {"amount": 16778.523489932886, "close": 0.01192, "count": 1, "high": 0.01192, "id": 1585266240, "low": 0.01192, "open": 0.01192, "vol": 20}, {"amount": 62237.17409587889, "close": 0.01189, "count": 2, "high": 0.01189, "id": 1585266300, "low": 0.01189, "open": 0.01189, "vol": 74}, {"amount": 57089.24314912177, "close": 0.01192, "count": 2, "high": 0.01192, "id": 1585266360, "low": 0.01191, "open": 0.01191, "vol": 68}, {"amount": 2203021.5430042995, "close": 0.01191, "count": 7, "high": 0.01192, "id": 1585266420, "low": 0.01191, "open": 0.01192, "vol": 2626}, {"amount": 3358.5222502099077, "close": 0.01191, "count": 1, "high": 0.01191, "id": 1585266480, "low": 0.01191, "open": 0.01191, "vol": 4}, {"amount": 28547.439126784215, "close": 0.01191, "count": 1, "high": 0.01191, "id": 1585266540, "low": 0.01191, "open": 0.01191, "vol": 34}, {"amount": 0, "close": 0.01191, "count": 0, "high": 0.01191, "id": 1585266600, "low": 0.01191, "open": 0.01191, "vol": 0}, {"amount": 0, "close": 0.01191, "count": 0, "high": 0.01191, "id": 1585266660, "low": 0.01191, "open": 0.01191, "vol": 0}, {"amount": 0, "close": 0.01191, "count": 0, "high": 0.01191, "id": 1585266720, "low": 0.01191, "open": 0.01191, "vol": 0}, {"amount": 0, "close": 0.01191, "count": 0, "high": 0.01191, "id": 1585266780, "low": 0.01191, "open": 0.01191, "vol": 0}, {"amount": 86830.87797401127, "close": 0.01198, "count": 2, "high": 0.01198, "id": 1585266840, "low": 0.01197, "open": 0.01197, "vol": 104}, {"amount": 0, "close": 0.01198, "count": 0, "high": 0.01198, "id": 1585266900, "low": 0.01198, "open": 0.01198, "vol": 0}, {"amount": 0, "close": 0.01198, "count": 0, "high": 0.01198, "id": 1585266960, "low": 0.01198, "open": 0.01198, "vol": 0}, {"amount": 0, "close": 0.01198, "count": 0, "high": 0.01198, "id": 1585267020, "low": 0.01198, "open": 0.01198, "vol": 0}, {"amount": 1306706.00693484, "close": 0.01196, "count": 8, "high": 0.01197, "id": 1585267080, "low": 0.01196, "open": 0.01196, "vol": 1564}, {"amount": 0, "close": 0.01196, "count": 0, "high": 0.01196, "id": 1585267140, "low": 0.01196, "open": 0.01196, "vol": 0}, {"amount": 58479.53216374269, "close": 0.01197, "count": 1, "high": 0.01197, "id": 1585267200, "low": 0.01197, "open": 0.01197, "vol": 70}, {"amount": 43405.676126878134, "close": 0.01198, "count": 1, "high": 0.01198, "id": 1585267260, "low": 0.01198, "open": 0.01198, "vol": 52}, {"amount": 73333.33333333333, "close": 0.012, "count": 2, "high": 0.012, "id": 1585267320, "low": 0.012, "open": 0.012, "vol": 88}, {"amount": 91602.96278615194, "close": 0.01201, "count": 8, "high": 0.01203, "id": 1585267380, "low": 0.01198, "open": 0.01203, "vol": 110}, {"amount": 5000, "close": 0.012, "count": 1, "high": 0.012, "id": 1585267440, "low": 0.012, "open": 0.012, "vol": 6}, {"amount": 66529.4703633536, "close": 0.01202, "count": 5, "high": 0.01203, "id": 1585267500, "low": 0.01201, "open": 0.01203, "vol": 80}, {"amount": 29950.083194675542, "close": 0.01202, "count": 1, "high": 0.01202, "id": 1585267560, "low": 0.01202, "open": 0.01202, "vol": 36}, {"amount": 3334959.942336849, "close": 0.01203, "count": 6, "high": 0.01204, "id": 1585267620, "low": 0.01203, "open": 0.01203, "vol": 4012}, {"amount": 89622.45014388043, "close": 0.01206, "count": 5, "high": 0.01206, "id": 1585267680, "low": 0.01204, "open": 0.01204, "vol": 108}, {"amount": 0, "close": 0.01206, "count": 0, "high": 0.01206, "id": 1585267740, "low": 0.01206, "open": 0.01206, "vol": 0}, {"amount": 361808.3819102232, "close": 0.01208, "count": 11, "high": 0.01214, "id": 1585267800, "low": 0.01208, "open": 0.01209, "vol": 438}, {"amount": 0, "close": 0.01208, "count": 0, "high": 0.01208, "id": 1585267860, "low": 0.01208, "open": 0.01208, "vol": 0}, {"amount": 102819.23714759536, "close": 0.01206, "count": 1, "high": 0.01206, "id": 1585267920, "low": 0.01206, "open": 0.01206, "vol": 124}, {"amount": 108153.078202995, "close": 0.01202, "count": 1, "high": 0.01202, "id": 1585267980, "low": 0.01202, "open": 0.01202, "vol": 130}, {"amount": 166112.95681063124, "close": 0.01204, "count": 1, "high": 0.01204, "id": 1585268040, "low": 0.01204, "open": 0.01204, "vol": 200}, {"amount": 248657.36189603092, "close": 0.01207, "count": 5, "high": 0.01207, "id": 1585268100, "low": 0.01205, "open": 0.01205, "vol": 300}, {"amount": 1657.0008285004142, "close": 0.01207, "count": 1, "high": 0.01207, "id": 1585268160, "low": 0.01207, "open": 0.01207, "vol": 2}, {"amount": 0, "close": 0.01207, "count": 0, "high": 0.01207, "id": 1585268220, "low": 0.01207, "open": 0.01207, "vol": 0}, {"amount": 126036.48424543947, "close": 0.01206, "count": 2, "high": 0.01206, "id": 1585268280, "low": 0.01206, "open": 0.01206, "vol": 152}, {"amount": 241546.69299937406, "close": 0.0121, "count": 5, "high": 0.0121, "id": 1585268340, "low": 0.01208, "open": 0.01208, "vol": 292}, {"amount": 84448.06643246127, "close": 0.01206, "count": 3, "high": 0.01208, "id": 1585268400, "low": 0.01206, "open": 0.01208, "vol": 102}, {"amount": 0, "close": 0.01206, "count": 0, "high": 0.01206, "id": 1585268460, "low": 0.01206, "open": 0.01206, "vol": 0}, {"amount": 31404.95867768595, "close": 0.0121, "count": 1, "high": 0.0121, "id": 1585268520, "low": 0.0121, "open": 0.0121, "vol": 38}, {"amount": 0, "close": 0.0121, "count": 0, "high": 0.0121, "id": 1585268580, "low": 0.0121, "open": 0.0121, "vol": 0}, {"amount": 530240.2651201326, "close": 0.01207, "count": 2, "high": 0.01207, "id": 1585268640, "low": 0.01207, "open": 0.01207, "vol": 640}, {"amount": 82781.45695364238, "close": 0.01208, "count": 1, "high": 0.01208, "id": 1585268700, "low": 0.01208, "open": 0.01208, "vol": 100}, {"amount": 1652.892561983471, "close": 0.0121, "count": 1, "high": 0.0121, "id": 1585268760, "low": 0.0121, "open": 0.0121, "vol": 2}, {"amount": 0, "close": 0.0121, "count": 0, "high": 0.0121, "id": 1585268820, "low": 0.0121, "open": 0.0121, "vol": 0}, {"amount": 0, "close": 0.0121, "count": 0, "high": 0.0121, "id": 1585268880, "low": 0.0121, "open": 0.0121, "vol": 0}, {"amount": 0, "close": 0.0121, "count": 0, "high": 0.0121, "id": 1585268940, "low": 0.0121, "open": 0.0121, "vol": 0}, {"amount": 0, "close": 0.0121, "count": 0, "high": 0.0121, "id": 1585269000, "low": 0.0121, "open": 0.0121, "vol": 0}, {"amount": 0, "close": 0.0121, "count": 0, "high": 0.0121, "id": 1585269060, "low": 0.0121, "open": 0.0121, "vol": 0}, {"amount": 33277.87021630615, "close": 0.01202, "count": 1, "high": 0.01202, "id": 1585269120, "low": 0.01202, "open": 0.01202, "vol": 40}, {"amount": 1662.510390689942, "close": 0.01203, "count": 1, "high": 0.01203, "id": 1585269180, "low": 0.01203, "open": 0.01203, "vol": 2}, {"amount": 0, "close": 0.01203, "count": 0, "high": 0.01203, "id": 1585269240, "low": 0.01203, "open": 0.01203, "vol": 0}, {"amount": 0, "close": 0.01203, "count": 0, "high": 0.01203, "id": 1585269300, "low": 0.01203, "open": 0.01203, "vol": 0}, {"amount": 0, "close": 0.01203, "count": 0, "high": 0.01203, "id": 1585269360, "low": 0.01203, "open": 0.01203, "vol": 0}, {"amount": 83333.33333333333, "close": 0.012, "count": 1, "high": 0.012, "id": 1585269420, "low": 0.012, "open": 0.012, "vol": 100}, {"amount": 381666.6666666667, "close": 0.012, "count": 2, "high": 0.012, "id": 1585269480, "low": 0.012, "open": 0.012, "vol": 458}, {"amount": 0, "close": 0.012, "count": 0, "high": 0.012, "id": 1585269540, "low": 0.012, "open": 0.012, "vol": 0}, {"amount": 0, "close": 0.012, "count": 0, "high": 0.012, "id": 1585269600, "low": 0.012, "open": 0.012, "vol": 0}, {"amount": 0, "close": 0.012, "count": 0, "high": 0.012, "id": 1585269660, "low": 0.012, "open": 0.012, "vol": 0}, {"amount": 0, "close": 0.012, "count": 0, "high": 0.012, "id": 1585269720, "low": 0.012, "open": 0.012, "vol": 0}, {"amount": 0, "close": 0.012, "count": 0, "high": 0.012, "id": 1585269780, "low": 0.012, "open": 0.012, "vol": 0}, {"amount": 0, "close": 0.012, "count": 0, "high": 0.012, "id": 1585269840, "low": 0.012, "open": 0.012, "vol": 0}, {"amount": 1663.8935108153078, "close": 0.01202, "count": 1, "high": 0.01202, "id": 1585269900, "low": 0.01202, "open": 0.01202, "vol": 2}, {"amount": 0, "close": 0.01202, "count": 0, "high": 0.01202, "id": 1585269960, "low": 0.01202, "open": 0.01202, "vol": 0}, {"amount": 0, "close": 0.01202, "count": 0, "high": 0.01202, "id": 1585270020, "low": 0.01202, "open": 0.01202, "vol": 0}, {"amount": 0, "close": 0.01202, "count": 0, "high": 0.01202, "id": 1585270080, "low": 0.01202, "open": 0.01202, "vol": 0}, {"amount": 1662.510390689942, "close": 0.01203, "count": 1, "high": 0.01203, "id": 1585270140, "low": 0.01203, "open": 0.01203, "vol": 2}, {"amount": 0, "close": 0.01203, "count": 0, "high": 0.01203, "id": 1585270200, "low": 0.01203, "open": 0.01203, "vol": 0}, {"amount": 24969.48835851802, "close": 0.01202, "count": 3, "high": 0.01202, "id": 1585270260, "low": 0.012, "open": 0.01201, "vol": 30}, {"amount": 0, "close": 0.01202, "count": 0, "high": 0.01202, "id": 1585270320, "low": 0.01202, "open": 0.01202, "vol": 0}, {"amount": 0, "close": 0.01202, "count": 0, "high": 0.01202, "id": 1585270380, "low": 0.01202, "open": 0.01202, "vol": 0}, {"amount": 0, "close": 0.01202, "count": 0, "high": 0.01202, "id": 1585270440, "low": 0.01202, "open": 0.01202, "vol": 0}, {"amount": 0, "close": 0.01202, "count": 0, "high": 0.01202, "id": 1585270500, "low": 0.01202, "open": 0.01202, "vol": 0}, {"amount": 0, "close": 0.01202, "count": 0, "high": 0.01202, "id": 1585270560, "low": 0.01202, "open": 0.01202, "vol": 0}, {"amount": 0, "close": 0.01202, "count": 0, "high": 0.01202, "id": 1585270620, "low": 0.01202, "open": 0.01202, "vol": 0}, {"amount": 0, "close": 0.01202, "count": 0, "high": 0.01202, "id": 1585270680, "low": 0.01202, "open": 0.01202, "vol": 0}, {"amount": 0, "close": 0.01202, "count": 0, "high": 0.01202, "id": 1585270740, "low": 0.01202, "open": 0.01202, "vol": 0}, {"amount": 157818.3967465869, "close": 0.01207, "count": 5, "high": 0.01207, "id": 1585270800, "low": 0.01203, "open": 0.01203, "vol": 190}, {"amount": 0, "close": 0.01207, "count": 0, "high": 0.01207, "id": 1585270860, "low": 0.01207, "open": 0.01207, "vol": 0}, {"amount": 0, "close": 0.01207, "count": 0, "high": 0.01207, "id": 1585270920, "low": 0.01207, "open": 0.01207, "vol": 0}, {"amount": 0, "close": 0.01207, "count": 0, "high": 0.01207, "id": 1585270980, "low": 0.01207, "open": 0.01207, "vol": 0}, {"amount": 0, "close": 0.01207, "count": 0, "high": 0.01207, "id": 1585271040, "low": 0.01207, "open": 0.01207, "vol": 0}, {"amount": 0, "close": 0.01207, "count": 0, "high": 0.01207, "id": 1585271100, "low": 0.01207, "open": 0.01207, "vol": 0}, {"amount": 29894.841009718966, "close": 0.01202, "count": 4, "high": 0.01206, "id": 1585271160, "low": 0.01202, "open": 0.01206, "vol": 36}, {"amount": 0, "close": 0.01202, "count": 0, "high": 0.01202, "id": 1585271220, "low": 0.01202, "open": 0.01202, "vol": 0}, {"amount": 0, "close": 0.01202, "count": 0, "high": 0.01202, "id": 1585271280, "low": 0.01202, "open": 0.01202, "vol": 0}, {"amount": 0, "close": 0.01202, "count": 0, "high": 0.01202, "id": 1585271340, "low": 0.01202, "open": 0.01202, "vol": 0}, {"amount": 3325.020781379884, "close": 0.01203, "count": 1, "high": 0.01203, "id": 1585271400, "low": 0.01203, "open": 0.01203, "vol": 4}, {"amount": 3330.5578684429643, "close": 0.01201, "count": 1, "high": 0.01201, "id": 1585271460, "low": 0.01201, "open": 0.01201, "vol": 4}, {"amount": 15000, "close": 0.012, "count": 2, "high": 0.012, "id": 1585271520, "low": 0.012, "open": 0.012, "vol": 18}, {"amount": 26600.16625103907, "close": 0.01203, "count": 1, "high": 0.01203, "id": 1585271580, "low": 0.01203, "open": 0.01203, "vol": 32}, {"amount": 29900.332225913622, "close": 0.01204, "count": 1, "high": 0.01204, "id": 1585271640, "low": 0.01204, "open": 0.01204, "vol": 36}, {"amount": 74750.83056478405, "close": 0.01204, "count": 1, "high": 0.01204, "id": 1585271700, "low": 0.01204, "open": 0.01204, "vol": 90}, {"amount": 104564.3153526971, "close": 0.01205, "count": 2, "high": 0.01205, "id": 1585271760, "low": 0.01205, "open": 0.01205, "vol": 126}, {"amount": 0, "close": 0.01205, "count": 0, "high": 0.01205, "id": 1585271820, "low": 0.01205, "open": 0.01205, "vol": 0}, {"amount": 0, "close": 0.01205, "count": 0, "high": 0.01205, "id": 1585271880, "low": 0.01205, "open": 0.01205, "vol": 0}, {"amount": 0, "close": 0.01205, "count": 0, "high": 0.01205, "id": 1585271940, "low": 0.01205, "open": 0.01205, "vol": 0}, {"amount": 0, "close": 0.01205, "count": 0, "high": 0.01205, "id": 1585272000, "low": 0.01205, "open": 0.01205, "vol": 0}, {"amount": 235880.39867109634, "close": 0.01204, "count": 2, "high": 0.01204, "id": 1585272060, "low": 0.01204, "open": 0.01204, "vol": 284}, {"amount": 1663.8935108153078, "close": 0.01202, "count": 1, "high": 0.01202, "id": 1585272120, "low": 0.01202, "open": 0.01202, "vol": 2}, {"amount": 397926.8524150008, "close": 0.01201, "count": 5, "high": 0.01202, "id": 1585272180, "low": 0.01201, "open": 0.01202, "vol": 478}, {"amount": 0, "close": 0.01201, "count": 0, "high": 0.01201, "id": 1585272240, "low": 0.01201, "open": 0.01201, "vol": 0}, {"amount": 0, "close": 0.01201, "count": 0, "high": 0.01201, "id": 1585272300, "low": 0.01201, "open": 0.01201, "vol": 0}, {"amount": 0, "close": 0.01201, "count": 0, "high": 0.01201, "id": 1585272360, "low": 0.01201, "open": 0.01201, "vol": 0}, {"amount": 0, "close": 0.01201, "count": 0, "high": 0.01201, "id": 1585272420, "low": 0.01201, "open": 0.01201, "vol": 0}, {"amount": 0, "close": 0.01201, "count": 0, "high": 0.01201, "id": 1585272480, "low": 0.01201, "open": 0.01201, "vol": 0}, {"amount": 0, "close": 0.01201, "count": 0, "high": 0.01201, "id": 1585272540, "low": 0.01201, "open": 0.01201, "vol": 0}, {"amount": 0, "close": 0.01201, "count": 0, "high": 0.01201, "id": 1585272600, "low": 0.01201, "open": 0.01201, "vol": 0}, {"amount": 0, "close": 0.01201, "count": 0, "high": 0.01201, "id": 1585272660, "low": 0.01201, "open": 0.01201, "vol": 0}, {"amount": 0, "close": 0.01201, "count": 0, "high": 0.01201, "id": 1585272720, "low": 0.01201, "open": 0.01201, "vol": 0}, {"amount": 0, "close": 0.01201, "count": 0, "high": 0.01201, "id": 1585272780, "low": 0.01201, "open": 0.01201, "vol": 0}, {"amount": 6722.689075630252, "close": 0.0119, "count": 1, "high": 0.0119, "id": 1585272840, "low": 0.0119, "open": 0.0119, "vol": 8}, {"amount": 7422818.791946309, "close": 0.01192, "count": 4, "high": 0.01192, "id": 1585272900, "low": 0.01192, "open": 0.01192, "vol": 8848}, {"amount": 95717.88413098236, "close": 0.01191, "count": 3, "high": 0.01191, "id": 1585272960, "low": 0.01191, "open": 0.01191, "vol": 114}, {"amount": 242016.80672268907, "close": 0.0119, "count": 4, "high": 0.0119, "id": 1585273020, "low": 0.0119, "open": 0.0119, "vol": 288}, {"amount": 203020.13422818793, "close": 0.01192, "count": 2, "high": 0.01192, "id": 1585273080, "low": 0.01192, "open": 0.01192, "vol": 242}, {"amount": 0, "close": 0.01192, "count": 0, "high": 0.01192, "id": 1585273140, "low": 0.01192, "open": 0.01192, "vol": 0}, {"amount": 33585.22250209907, "close": 0.01191, "count": 1, "high": 0.01191, "id": 1585273200, "low": 0.01191, "open": 0.01191, "vol": 40}, {"amount": 8403.361344537816, "close": 0.0119, "count": 1, "high": 0.0119, "id": 1585273260, "low": 0.0119, "open": 0.0119, "vol": 10}, {"amount": 0, "close": 0.0119, "count": 0, "high": 0.0119, "id": 1585273320, "low": 0.0119, "open": 0.0119, "vol": 0}, {"amount": 0, "close": 0.0119, "count": 0, "high": 0.0119, "id": 1585273380, "low": 0.0119, "open": 0.0119, "vol": 0}, {"amount": 0, "close": 0.0119, "count": 0, "high": 0.0119, "id": 1585273440, "low": 0.0119, "open": 0.0119, "vol": 0}, {"amount": 0, "close": 0.0119, "count": 0, "high": 0.0119, "id": 1585273500, "low": 0.0119, "open": 0.0119, "vol": 0}], "status": "ok", "ts": 1585273504433}