{"ch": "market.ETC_CW.kline.1min", "data": [{"amount": 826.9825289018661, "close": 5.03, "count": 7, "high": 5.033, "id": 1584314760, "low": 5.028, "open": 5.033, "vol": 416}, {"amount": 3791.110677725577, "close": 5.038, "count": 13, "high": 5.038, "id": 1584314820, "low": 5.024, "open": 5.024, "vol": 1908}, {"amount": 6652.680384982636, "close": 5.046, "count": 31, "high": 5.053, "id": 1584314880, "low": 5.032, "open": 5.035, "vol": 3356}, {"amount": 1928.585631378568, "close": 5.047, "count": 7, "high": 5.054, "id": 1584314940, "low": 5.047, "open": 5.054, "vol": 974}, {"amount": 766.6076112088354, "close": 5.032, "count": 4, "high": 5.036, "id": 1584315000, "low": 5.032, "open": 5.036, "vol": 386}, {"amount": 6315.508327877345, "close": 5.013, "count": 31, "high": 5.031, "id": 1584315060, "low": 5.013, "open": 5.031, "vol": 3170}, {"amount": 1830.3356209894214, "close": 5.005, "count": 8, "high": 5.011, "id": 1584315120, "low": 5, "open": 5.011, "vol": 916}, {"amount": 8913.822271484012, "close": 4.996, "count": 25, "high": 5.005, "id": 1584315180, "low": 4.987, "open": 5.005, "vol": 4454}, {"amount": 776.6261486493626, "close": 4.995, "count": 4, "high": 5.005, "id": 1584315240, "low": 4.995, "open": 5.005, "vol": 388}, {"amount": 2261.0390622642494, "close": 5.011, "count": 5, "high": 5.011, "id": 1584315300, "low": 4.995, "open": 5.001, "vol": 1130}, {"amount": 2723.800355801306, "close": 5.018, "count": 12, "high": 5.023, "id": 1584315360, "low": 5.01, "open": 5.012, "vol": 1366}, {"amount": 1838.143907835263, "close": 5.027, "count": 11, "high": 5.031, "id": 1584315420, "low": 5.019, "open": 5.019, "vol": 924}, {"amount": 3616.784924472389, "close": 5.028, "count": 11, "high": 5.028, "id": 1584315480, "low": 5.024, "open": 5.028, "vol": 1818}, {"amount": 39.7377309755613, "close": 5.033, "count": 1, "high": 5.033, "id": 1584315540, "low": 5.033, "open": 5.033, "vol": 20}, {"amount": 6504.547049389076, "close": 5.031, "count": 20, "high": 5.036, "id": 1584315600, "low": 5.02, "open": 5.028, "vol": 3270}, {"amount": 3858.732989281331, "close": 5.048, "count": 15, "high": 5.048, "id": 1584315660, "low": 5.028, "open": 5.04, "vol": 1942}, {"amount": 10157.40945975964, "close": 5.056, "count": 32, "high": 5.075, "id": 1584315720, "low": 5.051, "open": 5.051, "vol": 5140}, {"amount": 1922.0398535156228, "close": 5.066, "count": 9, "high": 5.071, "id": 1584315780, "low": 5.059, "open": 5.059, "vol": 974}, {"amount": 4777.301005235038, "close": 5.074, "count": 12, "high": 5.079, "id": 1584315840, "low": 5.068, "open": 5.068, "vol": 2424}, {"amount": 11216.593196227404, "close": 5.058, "count": 20, "high": 5.071, "id": 1584315900, "low": 5.052, "open": 5.071, "vol": 5682}, {"amount": 1673.7704762758615, "close": 5.066, "count": 16, "high": 5.068, "id": 1584315960, "low": 5.065, "open": 5.065, "vol": 848}, {"amount": 0, "close": 5.066, "count": 0, "high": 5.066, "id": 1584316020, "low": 5.066, "open": 5.066, "vol": 0}, {"amount": 244.66466939346722, "close": 5.068, "count": 2, "high": 5.069, "id": 1584316080, "low": 5.068, "open": 5.069, "vol": 124}, {"amount": 435.2126607319486, "close": 5.055, "count": 1, "high": 5.055, "id": 1584316140, "low": 5.055, "open": 5.055, "vol": 220}, {"amount": 3.952569169960474, "close": 5.06, "count": 1, "high": 5.06, "id": 1584316200, "low": 5.06, "open": 5.06, "vol": 2}, {"amount": 2555.6445377844034, "close": 5.052, "count": 10, "high": 5.052, "id": 1584316260, "low": 5.044, "open": 5.05, "vol": 1290}, {"amount": 1052.6811882934282, "close": 5.058, "count": 4, "high": 5.058, "id": 1584316320, "low": 5.05, "open": 5.053, "vol": 532}, {"amount": 3077.691720157957, "close": 5.05, "count": 13, "high": 5.051, "id": 1584316380, "low": 5.045, "open": 5.051, "vol": 1554}, {"amount": 5599.686237968745, "close": 5.038, "count": 26, "high": 5.051, "id": 1584316440, "low": 5.034, "open": 5.051, "vol": 2824}, {"amount": 4572.928525233712, "close": 5.037, "count": 20, "high": 5.037, "id": 1584316500, "low": 5.023, "open": 5.031, "vol": 2302}, {"amount": 2614.376362996056, "close": 5.041, "count": 12, "high": 5.045, "id": 1584316560, "low": 5.039, "open": 5.039, "vol": 1318}, {"amount": 419.96830427892235, "close": 5.048, "count": 2, "high": 5.048, "id": 1584316620, "low": 5.048, "open": 5.048, "vol": 212}, {"amount": 673.3223652815153, "close": 5.046, "count": 5, "high": 5.052, "id": 1584316680, "low": 5.046, "open": 5.052, "vol": 340}, {"amount": 784.0031676895665, "close": 5.051, "count": 2, "high": 5.051, "id": 1584316740, "low": 5.051, "open": 5.051, "vol": 396}, {"amount": 776.5593106652141, "close": 5.042, "count": 5, "high": 5.048, "id": 1584316800, "low": 5.042, "open": 5.048, "vol": 392}, {"amount": 3375.662769575211, "close": 5.014, "count": 21, "high": 5.038, "id": 1584316860, "low": 5.013, "open": 5.038, "vol": 1696}, {"amount": 25147.269642638686, "close": 4.946, "count": 129, "high": 5.012, "id": 1584316920, "low": 4.945, "open": 5.012, "vol": 12508}, {"amount": 12790.836129491005, "close": 4.963, "count": 50, "high": 4.963, "id": 1584316980, "low": 4.915, "open": 4.945, "vol": 6312}, {"amount": 12028.562576341825, "close": 4.952, "count": 45, "high": 4.977, "id": 1584317040, "low": 4.944, "open": 4.969, "vol": 5978}, {"amount": 17623.527127249094, "close": 4.948, "count": 30, "high": 4.959, "id": 1584317100, "low": 4.946, "open": 4.948, "vol": 8736}, {"amount": 1863.9829584245347, "close": 4.919, "count": 13, "high": 4.938, "id": 1584317160, "low": 4.918, "open": 4.938, "vol": 918}, {"amount": 13467.420851844527, "close": 4.95, "count": 34, "high": 4.95, "id": 1584317220, "low": 4.912, "open": 4.919, "vol": 6632}, {"amount": 5088.288993251918, "close": 4.925, "count": 24, "high": 4.951, "id": 1584317280, "low": 4.916, "open": 4.951, "vol": 2512}, {"amount": 7376.722879743262, "close": 4.941, "count": 32, "high": 4.944, "id": 1584317340, "low": 4.922, "open": 4.927, "vol": 3638}, {"amount": 1720.5563573062618, "close": 4.942, "count": 18, "high": 4.942, "id": 1584317400, "low": 4.93, "open": 4.942, "vol": 850}, {"amount": 18904.68744437708, "close": 4.964, "count": 86, "high": 4.985, "id": 1584317460, "low": 4.946, "open": 4.946, "vol": 9400}, {"amount": 7676.193562225944, "close": 4.959, "count": 23, "high": 4.97, "id": 1584317520, "low": 4.951, "open": 4.97, "vol": 3808}, {"amount": 3657.075586494073, "close": 4.95, "count": 20, "high": 4.959, "id": 1584317580, "low": 4.95, "open": 4.95, "vol": 1812}, {"amount": 4834.918123007911, "close": 4.95, "count": 16, "high": 4.953, "id": 1584317640, "low": 4.947, "open": 4.951, "vol": 2394}, {"amount": 6238.243973905311, "close": 4.969, "count": 44, "high": 4.978, "id": 1584317700, "low": 4.949, "open": 4.949, "vol": 3098}, {"amount": 6388.818352370002, "close": 5.006, "count": 66, "high": 5.006, "id": 1584317760, "low": 4.965, "open": 4.972, "vol": 3190}, {"amount": 2643.330863868768, "close": 4.993, "count": 16, "high": 4.999, "id": 1584317820, "low": 4.988, "open": 4.995, "vol": 1320}, {"amount": 6731.983019911575, "close": 4.995, "count": 35, "high": 5.014, "id": 1584317880, "low": 4.995, "open": 4.996, "vol": 3366}, {"amount": 15301.39171979766, "close": 5.017, "count": 58, "high": 5.02, "id": 1584317940, "low": 4.989, "open": 4.993, "vol": 7656}, {"amount": 3411.391732469689, "close": 5.013, "count": 22, "high": 5.022, "id": 1584318000, "low": 5.011, "open": 5.019, "vol": 1710}, {"amount": 2484.501386217189, "close": 5.015, "count": 10, "high": 5.015, "id": 1584318060, "low": 5.004, "open": 5.009, "vol": 1244}, {"amount": 1676.557181127419, "close": 4.992, "count": 12, "high": 5.005, "id": 1584318120, "low": 4.992, "open": 5.005, "vol": 838}, {"amount": 328.3523860331391, "close": 4.995, "count": 2, "high": 4.995, "id": 1584318180, "low": 4.993, "open": 4.993, "vol": 164}, {"amount": 2453.35943718667, "close": 4.993, "count": 7, "high": 4.994, "id": 1584318240, "low": 4.987, "open": 4.99, "vol": 1224}, {"amount": 5715.837988580831, "close": 4.998, "count": 24, "high": 5.004, "id": 1584318300, "low": 4.995, "open": 4.996, "vol": 2858}, {"amount": 2902.5253352594923, "close": 4.99, "count": 14, "high": 5, "id": 1584318360, "low": 4.99, "open": 4.997, "vol": 1450}, {"amount": 2276.0225840322673, "close": 5.002, "count": 6, "high": 5.002, "id": 1584318420, "low": 4.995, "open": 4.995, "vol": 1138}, {"amount": 6620.768565300111, "close": 4.992, "count": 34, "high": 5.004, "id": 1584318480, "low": 4.991, "open": 4.999, "vol": 3308}, {"amount": 1209.9745073973686, "close": 4.991, "count": 5, "high": 4.995, "id": 1584318540, "low": 4.991, "open": 4.991, "vol": 604}, {"amount": 8357.370161367999, "close": 4.992, "count": 19, "high": 5, "id": 1584318600, "low": 4.992, "open": 4.995, "vol": 4176}, {"amount": 5177.478076272718, "close": 4.981, "count": 26, "high": 4.992, "id": 1584318660, "low": 4.981, "open": 4.992, "vol": 2582}, {"amount": 12850.047144328064, "close": 5.002, "count": 30, "high": 5.002, "id": 1584318720, "low": 4.982, "open": 4.982, "vol": 6418}, {"amount": 2892.8992268769634, "close": 5.007, "count": 19, "high": 5.013, "id": 1584318780, "low": 5.004, "open": 5.004, "vol": 1448}, {"amount": 2273.0816718529036, "close": 5.003, "count": 8, "high": 5.009, "id": 1584318840, "low": 5.003, "open": 5.005, "vol": 1138}, {"amount": 1770.9850862518017, "close": 5.01, "count": 8, "high": 5.016, "id": 1584318900, "low": 5.006, "open": 5.006, "vol": 888}, {"amount": 1041.4136575576024, "close": 5.013, "count": 3, "high": 5.013, "id": 1584318960, "low": 5.011, "open": 5.011, "vol": 522}, {"amount": 4202.763093457863, "close": 5.028, "count": 10, "high": 5.029, "id": 1584319020, "low": 5.019, "open": 5.019, "vol": 2112}, {"amount": 478.0639769969871, "close": 5.027, "count": 6, "high": 5.027, "id": 1584319080, "low": 5.019, "open": 5.02, "vol": 240}, {"amount": 3282.480214105519, "close": 5.031, "count": 10, "high": 5.031, "id": 1584319140, "low": 5.024, "open": 5.03, "vol": 1650}, {"amount": 4128.00792421471, "close": 5.028, "count": 22, "high": 5.052, "id": 1584319200, "low": 5.028, "open": 5.038, "vol": 2078}, {"amount": 4555.221592419122, "close": 5.004, "count": 15, "high": 5.019, "id": 1584319260, "low": 5.004, "open": 5.017, "vol": 2282}, {"amount": 1634.9593121088765, "close": 5.01, "count": 13, "high": 5.018, "id": 1584319320, "low": 5.01, "open": 5.012, "vol": 820}, {"amount": 2133.976714105853, "close": 5.01, "count": 13, "high": 5.01, "id": 1584319380, "low": 5.001, "open": 5.005, "vol": 1068}, {"amount": 1173.4567643542152, "close": 5.009, "count": 4, "high": 5.013, "id": 1584319440, "low": 5.009, "open": 5.013, "vol": 588}, {"amount": 139.86013986013987, "close": 5.005, "count": 2, "high": 5.005, "id": 1584319500, "low": 5.005, "open": 5.005, "vol": 70}, {"amount": 319.99682525992466, "close": 4.999, "count": 7, "high": 5.005, "id": 1584319560, "low": 4.999, "open": 5.005, "vol": 160}, {"amount": 924, "close": 5, "count": 2, "high": 5, "id": 1584319620, "low": 5, "open": 5, "vol": 462}, {"amount": 1082.5008469059042, "close": 5.001, "count": 4, "high": 5.011, "id": 1584319680, "low": 5.001, "open": 5.007, "vol": 542}, {"amount": 2921.834607384234, "close": 5.018, "count": 14, "high": 5.019, "id": 1584319740, "low": 5.002, "open": 5.002, "vol": 1464}, {"amount": 1376.0648667411335, "close": 5.014, "count": 5, "high": 5.018, "id": 1584319800, "low": 5.014, "open": 5.015, "vol": 690}, {"amount": 2022.9609424725502, "close": 5.006, "count": 7, "high": 5.006, "id": 1584319860, "low": 5, "open": 5.004, "vol": 1012}, {"amount": 0, "close": 5.006, "count": 0, "high": 5.006, "id": 1584319920, "low": 5.006, "open": 5.006, "vol": 0}, {"amount": 2024.3601495216526, "close": 4.997, "count": 8, "high": 5, "id": 1584319980, "low": 4.996, "open": 5, "vol": 1012}, {"amount": 256.1536922153292, "close": 4.997, "count": 4, "high": 4.997, "id": 1584320040, "low": 4.997, "open": 4.997, "vol": 128}, {"amount": 11823.278683977005, "close": 4.977, "count": 55, "high": 4.995, "id": 1584320100, "low": 4.972, "open": 4.995, "vol": 5890}, {"amount": 5484.893875763527, "close": 4.988, "count": 15, "high": 4.988, "id": 1584320160, "low": 4.983, "open": 4.983, "vol": 2734}, {"amount": 903.3092484293966, "close": 4.977, "count": 6, "high": 4.985, "id": 1584320220, "low": 4.977, "open": 4.985, "vol": 450}, {"amount": 639.0279530211966, "close": 4.976, "count": 3, "high": 4.977, "id": 1584320280, "low": 4.976, "open": 4.977, "vol": 318}, {"amount": 3241.7146068233365, "close": 4.972, "count": 9, "high": 4.975, "id": 1584320340, "low": 4.972, "open": 4.975, "vol": 1612}, {"amount": 3111.7260106648855, "close": 4.956, "count": 15, "high": 4.969, "id": 1584320400, "low": 4.956, "open": 4.969, "vol": 1544}, {"amount": 14756.977452569832, "close": 4.959, "count": 54, "high": 4.959, "id": 1584320460, "low": 4.939, "open": 4.955, "vol": 7306}, {"amount": 2320.291857696243, "close": 4.974, "count": 13, "high": 4.974, "id": 1584320520, "low": 4.96, "open": 4.962, "vol": 1152}, {"amount": 4036.493198256542, "close": 4.986, "count": 18, "high": 4.986, "id": 1584320580, "low": 4.972, "open": 4.972, "vol": 2010}, {"amount": 1527.451966157538, "close": 4.99, "count": 5, "high": 4.99, "id": 1584320640, "low": 4.986, "open": 4.989, "vol": 762}, {"amount": 3517.1369378247196, "close": 4.974, "count": 13, "high": 4.984, "id": 1584320700, "low": 4.972, "open": 4.984, "vol": 1750}, {"amount": 672.8444802578566, "close": 4.964, "count": 2, "high": 4.964, "id": 1584320760, "low": 4.964, "open": 4.964, "vol": 334}, {"amount": 983.5621869584523, "close": 4.959, "count": 2, "high": 4.962, "id": 1584320820, "low": 4.959, "open": 4.962, "vol": 488}, {"amount": 7131.491625694184, "close": 4.975, "count": 19, "high": 4.975, "id": 1584320880, "low": 4.956, "open": 4.956, "vol": 3538}, {"amount": 1086.1065700018676, "close": 4.967, "count": 3, "high": 4.973, "id": 1584320940, "low": 4.967, "open": 4.973, "vol": 540}, {"amount": 3684.4747592044378, "close": 4.976, "count": 22, "high": 4.976, "id": 1584321000, "low": 4.967, "open": 4.967, "vol": 1832}, {"amount": 7913.110312709444, "close": 4.994, "count": 57, "high": 4.994, "id": 1584321060, "low": 4.972, "open": 4.972, "vol": 3942}, {"amount": 2384.623054726571, "close": 4.983, "count": 17, "high": 4.996, "id": 1584321120, "low": 4.983, "open": 4.996, "vol": 1190}, {"amount": 1325.3682803034899, "close": 4.981, "count": 12, "high": 4.982, "id": 1584321180, "low": 4.977, "open": 4.982, "vol": 660}, {"amount": 41959.03094567335, "close": 5, "count": 86, "high": 5, "id": 1584321240, "low": 4.982, "open": 4.982, "vol": 20936}, {"amount": 8646.788665144306, "close": 4.997, "count": 37, "high": 5.004, "id": 1584321300, "low": 4.992, "open": 5.001, "vol": 4324}, {"amount": 1478.104468358001, "close": 4.99, "count": 10, "high": 5.002, "id": 1584321360, "low": 4.99, "open": 5.002, "vol": 738}, {"amount": 45095.90045862044, "close": 4.979, "count": 25, "high": 4.991, "id": 1584321420, "low": 4.979, "open": 4.991, "vol": 22494}, {"amount": 7147.917074983895, "close": 4.976, "count": 16, "high": 4.976, "id": 1584321480, "low": 4.968, "open": 4.97, "vol": 3554}, {"amount": 1690.8212560386473, "close": 4.968, "count": 2, "high": 4.968, "id": 1584321540, "low": 4.968, "open": 4.968, "vol": 840}, {"amount": 80.43434546551377, "close": 4.973, "count": 1, "high": 4.973, "id": 1584321600, "low": 4.973, "open": 4.973, "vol": 40}, {"amount": 15395.76357397826, "close": 4.976, "count": 24, "high": 4.985, "id": 1584321660, "low": 4.976, "open": 4.979, "vol": 7672}, {"amount": 7607.218382983689, "close": 4.967, "count": 13, "high": 4.977, "id": 1584321720, "low": 4.967, "open": 4.977, "vol": 3782}, {"amount": 7341.883738351736, "close": 4.966, "count": 8, "high": 4.967, "id": 1584321780, "low": 4.966, "open": 4.967, "vol": 3646}, {"amount": 177.27639000805803, "close": 4.964, "count": 1, "high": 4.964, "id": 1584321840, "low": 4.964, "open": 4.964, "vol": 88}, {"amount": 0, "close": 4.964, "count": 0, "high": 4.964, "id": 1584321900, "low": 4.964, "open": 4.964, "vol": 0}, {"amount": 44.256688795011065, "close": 4.971, "count": 1, "high": 4.971, "id": 1584321960, "low": 4.971, "open": 4.971, "vol": 22}, {"amount": 470.6873563016784, "close": 4.973, "count": 4, "high": 4.973, "id": 1584322020, "low": 4.971, "open": 4.972, "vol": 234}, {"amount": 8980.955431205768, "close": 4.982, "count": 12, "high": 4.985, "id": 1584322080, "low": 4.976, "open": 4.976, "vol": 4474}, {"amount": 2583.9011727742736, "close": 5.002, "count": 32, "high": 5.002, "id": 1584322140, "low": 4.986, "open": 4.987, "vol": 1290}, {"amount": 1596.9059869015523, "close": 4.992, "count": 7, "high": 5.01, "id": 1584322200, "low": 4.991, "open": 5.009, "vol": 798}, {"amount": 13950.780248549336, "close": 4.987, "count": 7, "high": 4.991, "id": 1584322260, "low": 4.987, "open": 4.989, "vol": 6962}, {"amount": 4228.984078614245, "close": 4.986, "count": 10, "high": 4.986, "id": 1584322320, "low": 4.983, "open": 4.986, "vol": 2108}, {"amount": 19096.484884873014, "close": 4.991, "count": 30, "high": 4.997, "id": 1584322380, "low": 4.987, "open": 4.988, "vol": 9536}, {"amount": 356.6580455138462, "close": 4.981, "count": 4, "high": 4.991, "id": 1584322440, "low": 4.981, "open": 4.991, "vol": 178}, {"amount": 7816.291551334006, "close": 4.985, "count": 11, "high": 4.987, "id": 1584322500, "low": 4.972, "open": 4.976, "vol": 3894}, {"amount": 1123.852563745983, "close": 4.984, "count": 3, "high": 4.987, "id": 1584322560, "low": 4.982, "open": 4.982, "vol": 560}, {"amount": 493.5400220327851, "close": 4.983, "count": 4, "high": 4.985, "id": 1584322620, "low": 4.983, "open": 4.985, "vol": 246}, {"amount": 86627.14288198765, "close": 4.974, "count": 18, "high": 4.983, "id": 1584322680, "low": 4.974, "open": 4.983, "vol": 43164}, {"amount": 1796.2889381164948, "close": 4.973, "count": 3, "high": 4.981, "id": 1584322740, "low": 4.973, "open": 4.981, "vol": 894}, {"amount": 2782.6330549343234, "close": 4.965, "count": 9, "high": 4.972, "id": 1584322800, "low": 4.965, "open": 4.971, "vol": 1382}, {"amount": 8655.172815712509, "close": 4.952, "count": 34, "high": 4.965, "id": 1584322860, "low": 4.945, "open": 4.965, "vol": 4290}, {"amount": 501.0109174182724, "close": 4.95, "count": 5, "high": 4.95, "id": 1584322920, "low": 4.949, "open": 4.95, "vol": 248}, {"amount": 1239.5020071775791, "close": 4.954, "count": 5, "high": 4.957, "id": 1584322980, "low": 4.953, "open": 4.953, "vol": 614}, {"amount": 1191.6206255906595, "close": 4.948, "count": 5, "high": 4.952, "id": 1584323040, "low": 4.948, "open": 4.949, "vol": 590}, {"amount": 12951.303006425604, "close": 4.961, "count": 27, "high": 4.961, "id": 1584323100, "low": 4.949, "open": 4.949, "vol": 6418}, {"amount": 1026.7548620833873, "close": 4.97, "count": 8, "high": 4.97, "id": 1584323160, "low": 4.966, "open": 4.966, "vol": 510}, {"amount": 1194.4500301628796, "close": 4.973, "count": 4, "high": 4.973, "id": 1584323220, "low": 4.973, "open": 4.973, "vol": 594}, {"amount": 3617.7546545133687, "close": 4.97, "count": 13, "high": 4.973, "id": 1584323280, "low": 4.967, "open": 4.973, "vol": 1798}, {"amount": 7156.210853924985, "close": 4.982, "count": 20, "high": 4.985, "id": 1584323340, "low": 4.97, "open": 4.97, "vol": 3562}, {"amount": 4955.361037374562, "close": 4.96, "count": 9, "high": 4.977, "id": 1584323400, "low": 4.96, "open": 4.977, "vol": 2466}, {"amount": 298.9818931720633, "close": 4.946, "count": 3, "high": 4.955, "id": 1584323460, "low": 4.946, "open": 4.955, "vol": 148}, {"amount": 4055.3751181285284, "close": 4.95, "count": 8, "high": 4.95, "id": 1584323520, "low": 4.944, "open": 4.944, "vol": 2006}, {"amount": 3623.0104529188848, "close": 4.963, "count": 9, "high": 4.964, "id": 1584323580, "low": 4.956, "open": 4.956, "vol": 1798}, {"amount": 0, "close": 4.963, "count": 0, "high": 4.963, "id": 1584323640, "low": 4.963, "open": 4.963, "vol": 0}, {"amount": 0, "close": 4.963, "count": 0, "high": 4.963, "id": 1584323700, "low": 4.963, "open": 4.963, "vol": 0}, {"amount": 0, "close": 4.963, "count": 0, "high": 4.963, "id": 1584323760, "low": 4.963, "open": 4.963, "vol": 0}, {"amount": 0, "close": 4.963, "count": 0, "high": 4.963, "id": 1584323820, "low": 4.963, "open": 4.963, "vol": 0}, {"amount": 0, "close": 4.963, "count": 0, "high": 4.963, "id": 1584323880, "low": 4.963, "open": 4.963, "vol": 0}, {"amount": 923.5093354748043, "close": 4.981, "count": 2, "high": 4.981, "id": 1584323940, "low": 4.981, "open": 4.981, "vol": 460}, {"amount": 746.1455115179311, "close": 4.98, "count": 8, "high": 4.988, "id": 1584324000, "low": 4.98, "open": 4.987, "vol": 372}, {"amount": 8.02971000762351, "close": 4.982, "count": 2, "high": 4.982, "id": 1584324060, "low": 4.981, "open": 4.981, "vol": 4}, {"amount": 0, "close": 4.982, "count": 0, "high": 4.982, "id": 1584324120, "low": 4.982, "open": 4.982, "vol": 0}, {"amount": 1146.6807769144546, "close": 4.989, "count": 9, "high": 4.992, "id": 1584324180, "low": 4.985, "open": 4.985, "vol": 572}, {"amount": 3273.2537877640093, "close": 5.003, "count": 24, "high": 5.005, "id": 1584324240, "low": 4.993, "open": 4.993, "vol": 1636}, {"amount": 4225.219295605054, "close": 5.006, "count": 10, "high": 5.011, "id": 1584324300, "low": 5.002, "open": 5.002, "vol": 2116}, {"amount": 2893.506982062959, "close": 5.013, "count": 18, "high": 5.018, "id": 1584324360, "low": 5.008, "open": 5.008, "vol": 1450}, {"amount": 3868.832805868959, "close": 5.049, "count": 26, "high": 5.054, "id": 1584324420, "low": 5.018, "open": 5.02, "vol": 1950}, {"amount": 12295.830651920183, "close": 5.054, "count": 57, "high": 5.075, "id": 1584324480, "low": 5.049, "open": 5.052, "vol": 6218}, {"amount": 6503.96269350352, "close": 5.036, "count": 33, "high": 5.053, "id": 1584324540, "low": 5.03, "open": 5.053, "vol": 3278}, {"amount": 2878.11347162976, "close": 5.04, "count": 12, "high": 5.044, "id": 1584324600, "low": 5.035, "open": 5.036, "vol": 1450}, {"amount": 3182.7321547185707, "close": 5.044, "count": 21, "high": 5.052, "id": 1584324660, "low": 5.039, "open": 5.043, "vol": 1606}, {"amount": 3138.4256224560963, "close": 5.041, "count": 12, "high": 5.047, "id": 1584324720, "low": 5.04, "open": 5.047, "vol": 1582}, {"amount": 4910.738700030676, "close": 5.039, "count": 10, "high": 5.044, "id": 1584324780, "low": 5.039, "open": 5.044, "vol": 2476}, {"amount": 5806.528965427483, "close": 5.021, "count": 18, "high": 5.038, "id": 1584324840, "low": 5.018, "open": 5.038, "vol": 2916}, {"amount": 4963.412549309652, "close": 5.014, "count": 26, "high": 5.019, "id": 1584324900, "low": 5.007, "open": 5.019, "vol": 2488}, {"amount": 259.40538631525965, "close": 5.013, "count": 6, "high": 5.013, "id": 1584324960, "low": 5.009, "open": 5.012, "vol": 130}, {"amount": 2778.9766510502905, "close": 5, "count": 9, "high": 5.005, "id": 1584325020, "low": 4.999, "open": 5.005, "vol": 1390}, {"amount": 1472.6446293150495, "close": 5.002, "count": 5, "high": 5.002, "id": 1584325080, "low": 4.993, "open": 4.993, "vol": 736}, {"amount": 8.00480416403601, "close": 4.995, "count": 2, "high": 4.999, "id": 1584325140, "low": 4.995, "open": 4.999, "vol": 4}, {"amount": 4677.2776545542665, "close": 4.974, "count": 13, "high": 4.991, "id": 1584325200, "low": 4.974, "open": 4.991, "vol": 2332}, {"amount": 8.04424407037294, "close": 4.971, "count": 2, "high": 4.974, "id": 1584325260, "low": 4.971, "open": 4.974, "vol": 4}, {"amount": 4.023335345001006, "close": 4.971, "count": 1, "high": 4.971, "id": 1584325320, "low": 4.971, "open": 4.971, "vol": 2}, {"amount": 358.13598890338216, "close": 4.965, "count": 4, "high": 4.971, "id": 1584325380, "low": 4.965, "open": 4.971, "vol": 178}, {"amount": 2871.122250074311, "close": 4.987, "count": 14, "high": 4.987, "id": 1584325440, "low": 4.961, "open": 4.963, "vol": 1428}, {"amount": 1881.2508855718825, "close": 4.997, "count": 11, "high": 5.002, "id": 1584325500, "low": 4.988, "open": 4.988, "vol": 940}, {"amount": 885.5963546869784, "close": 4.984, "count": 5, "high": 4.995, "id": 1584325560, "low": 4.984, "open": 4.995, "vol": 442}, {"amount": 356.5705128205128, "close": 4.992, "count": 1, "high": 4.992, "id": 1584325620, "low": 4.992, "open": 4.992, "vol": 178}, {"amount": 0, "close": 4.992, "count": 0, "high": 4.992, "id": 1584325680, "low": 4.992, "open": 4.992, "vol": 0}, {"amount": 961.7311160088159, "close": 4.991, "count": 1, "high": 4.991, "id": 1584325740, "low": 4.991, "open": 4.991, "vol": 480}, {"amount": 585.8747993579454, "close": 4.984, "count": 2, "high": 4.984, "id": 1584325800, "low": 4.984, "open": 4.984, "vol": 292}, {"amount": 1398.5485246939802, "close": 4.961, "count": 9, "high": 4.966, "id": 1584325860, "low": 4.961, "open": 4.966, "vol": 694}, {"amount": 986.1868367449761, "close": 4.967, "count": 2, "high": 4.969, "id": 1584325920, "low": 4.967, "open": 4.969, "vol": 490}, {"amount": 2012.5469058852927, "close": 4.985, "count": 6, "high": 4.985, "id": 1584325980, "low": 4.972, "open": 4.972, "vol": 1002}, {"amount": 185.1479170859328, "close": 4.969, "count": 2, "high": 4.969, "id": 1584326040, "low": 4.969, "open": 4.969, "vol": 92}, {"amount": 976.8537990614054, "close": 4.992, "count": 5, "high": 4.992, "id": 1584326100, "low": 4.975, "open": 4.975, "vol": 486}, {"amount": 4937.825770321793, "close": 4.981, "count": 13, "high": 4.997, "id": 1584326160, "low": 4.981, "open": 4.997, "vol": 2464}, {"amount": 200.94040302432992, "close": 4.976, "count": 2, "high": 4.977, "id": 1584326220, "low": 4.976, "open": 4.977, "vol": 100}, {"amount": 1611.4540240676822, "close": 4.983, "count": 5, "high": 4.983, "id": 1584326280, "low": 4.976, "open": 4.976, "vol": 802}, {"amount": 1114.9437844558959, "close": 4.985, "count": 5, "high": 4.991, "id": 1584326340, "low": 4.985, "open": 4.991, "vol": 556}, {"amount": 24.106066693451186, "close": 4.978, "count": 1, "high": 4.978, "id": 1584326400, "low": 4.978, "open": 4.978, "vol": 12}, {"amount": 0, "close": 4.978, "count": 0, "high": 4.978, "id": 1584326460, "low": 4.978, "open": 4.978, "vol": 0}, {"amount": 0, "close": 4.978, "count": 0, "high": 4.978, "id": 1584326520, "low": 4.978, "open": 4.978, "vol": 0}, {"amount": 289.68014484007244, "close": 4.971, "count": 1, "high": 4.971, "id": 1584326580, "low": 4.971, "open": 4.971, "vol": 144}, {"amount": 1105.7781986539133, "close": 4.974, "count": 3, "high": 4.974, "id": 1584326640, "low": 4.973, "open": 4.973, "vol": 550}, {"amount": 0, "close": 4.974, "count": 0, "high": 4.974, "id": 1584326700, "low": 4.974, "open": 4.974, "vol": 0}], "status": "ok", "ts": 1584326704543}